{"cameraMode":{"drawMode":0,"name":"Shaded","section":"Shading Mode"},"sceneLighting":true,"audioPlay":false,"sceneViewState":{"showFog":true,"showMaterialUpdate":false,"showSkybox":true,"showFlares":true,"showImageEffects":true,"showParticleSystems":true},"in2DMode":false,"pivot":{"x":19.2080078125,"y":-5.675657749176025,"z":-23.138776779174806},"rotation":{"x":-0.009324737824499607,"y":0.9615089297294617,"z":0.032884735614061359,"w":0.27263936400413515},"size":179.88787841796876,"orthographic":false}